wq/build/__init__.py
wq/build/decorators.py
wq/build/commands/__init__.py
wq/build/commands/collect.py
wq/build/commands/icons.py
wq/build/commands/make_docs.py
wq/build/commands/movefiles.py
wq/build/commands/serviceworker.py
wq/build/commands/setversion.py
wq/build/management/__init__.py
wq/build/management/commands/__init__.py
wq/build/management/commands/_base.py
wq/build/management/commands/collectjson.py
wq/build/management/commands/deploy.py
wq/build/management/commands/icons.py
wq/build/management/commands/movefiles.py
wq/build/management/commands/serviceworker.py
wq/build/management/commands/setversion.py
wq.build-2.1.0.dist-info/LICENSE
wq.build-2.1.0.dist-info/METADATA
wq.build-2.1.0.dist-info/WHEEL
wq.build-2.1.0.dist-info/entry_points.txt
wq.build-2.1.0.dist-info/top_level.txt
wq.build-2.1.0.dist-info/RECORD
