Metadata-Version: 2.1
Name: wq.build
Version: 2.1.0
Summary: The wq command line tool.
Author-email: "S. Andrew Sheppard" <andrew@wq.io>
License: MIT
Project-URL: Homepage, https://wq.io/wq.build/
Project-URL: Documentation, https://wq.io/
Project-URL: Source, https://github.com/wq/wq.build
Project-URL: Release Notes, https://github.com/wq/wq.build/releases
Project-URL: Issues, https://github.com/wq/wq.build/issues
Project-URL: Tests, https://github.com/wq/wq.build/actions/workflows/test.yml
Classifier: Development Status :: 5 - Production/Stable
Classifier: Environment :: Web Environment
Classifier: License :: OSI Approved :: MIT License
Classifier: Natural Language :: English
Classifier: Programming Language :: JavaScript
Classifier: Programming Language :: Python :: 3
Classifier: Programming Language :: Python :: 3.8
Classifier: Programming Language :: Python :: 3.9
Classifier: Programming Language :: Python :: 3.10
Classifier: Programming Language :: Python :: 3.11
Classifier: Programming Language :: Python :: 3.12
Classifier: Framework :: Django
Classifier: Framework :: Django :: 4.0
Classifier: Framework :: Django :: 4.1
Classifier: Framework :: Django :: 4.2
Classifier: Framework :: Django :: 5.0
Classifier: Topic :: Software Development :: Libraries :: Application Frameworks
Classifier: Topic :: Software Development :: Build Tools
Requires-Python: >=3.8
License-File: LICENSE
Requires-Dist: click >8
Requires-Dist: django-click
Requires-Dist: PyYAML
Requires-Dist: Pillow
